utilmy/__init__.py
utilmy/abash.py
utilmy/adatasets.py
utilmy/cli.py
utilmy/data.py
utilmy/dates.py
utilmy/debug.py
utilmy/decorators.py
utilmy/distributed.py
utilmy/iio.py
utilmy/nnumpy.py
utilmy/oos.py
utilmy/parallel.py
utilmy/ppandas.py
utilmy/ppolars.py
utilmy/util_batch.py
utilmy/util_code.py
utilmy/util_colab.py
utilmy/util_conda.py
utilmy/util_cpu.py
utilmy/util_download.py
utilmy/util_numba.py
utilmy/util_zip.py
utilmy/utilmy_base.py
utilmy/utils.py
utilmy/z_test.py
utilmy/zdocstring.py
utilmy/cloud/__init__.py
utilmy/cloud/aws/__init__.py
utilmy/cloud/aws/util_aws.py
utilmy/cloud/aws/util_aws_daemon.py
utilmy/cloud/aws/autoscale_aws/__init__.py
utilmy/cloud/aws/autoscale_aws/batch_daemon_autoscale_cli.py
utilmy/cloud/aws/autoscale_aws/batch_daemon_launch_cli.py
utilmy/cloud/aws/autoscale_aws/batch_daemon_monitor_cli.py
utilmy/cloud/aws/autoscale_aws/cli.py
utilmy/cloud/aws/autoscale_aws/config.toml
utilmy/cloud/aws/autoscale_aws/util_aws.py
utilmy/cloud/aws/autoscale_aws/util_batch.py
utilmy/cloud/aws/autoscale_aws/util_cpu.py
utilmy/cloud/aws/autoscale_aws/util_log.py
utilmy/cloud/aws/autoscale_aws/z_batch_lambda_run.py
utilmy/cloud/aws/autoscale_aws/aws/aws_spot_price.sh
utilmy/cloud/aws/autoscale_aws/aws/ec2_spot_t3small.json
utilmy/cloud/aws/autoscale_aws/aws/lambda/main.py
utilmy/cloud/aws/autoscale_aws/task_template/main.sh
utilmy/cloud/aws/autoscale_aws/task_template/main_run.py
utilmy/cloud/aws/autoscale_aws/task_template/task_config.py
utilmy/cloud/aws/autoscale_aws/test/out/task_demo_qstart/result0.txt
utilmy/cloud/aws/autoscale_aws/test/out/task_demo_qstart/result1.txt
utilmy/cloud/aws/autoscale_aws/test/out/task_demo_qstart/result10.txt
utilmy/cloud/aws/autoscale_aws/test/out/task_demo_qstart/result11.txt
utilmy/cloud/aws/autoscale_aws/test/out/task_demo_qstart/result2.txt
utilmy/cloud/aws/autoscale_aws/test/out/task_demo_qstart/result3.txt
utilmy/cloud/aws/autoscale_aws/test/out/task_demo_qstart/result4.txt
utilmy-0.1.17154240.dist-info/METADATA
utilmy-0.1.17154240.dist-info/WHEEL
utilmy-0.1.17154240.dist-info/entry_points.txt
utilmy-0.1.17154240.dist-info/top_level.txt
utilmy-0.1.17154240.dist-info/RECORD
